Workbook

Sheet Panel
A1: PANEL · DOS NEGOCIOS, LADO A LADO
A2: Escribe en las celdas verdes, en las dos columnas. La de la izquierda es tu referente: un negocio real que investigues, parecido o no al tuyo, para comparar parejo. Los dos usan los mismos tres movimientos. Lee cruzando el renglón.
A4: Nombre del referente | B4: Investiga un negocio real y escribe su nombre aquí | E4: De dónde salen sus números | F4: Escribe de dónde sacaste esos números (una fuente, una entrevista, el sitio del negocio)
A6: LOS SUPUESTOS Y LOS MOVIMIENTOS | E6: EL MES ACTUAL, CUÁNTO SUMA CADA CAMINO Y DÓNDE SE VOLTEA
A7: Concepto | B7: =$B$4 | C7: Tu negocio | E7: Resultado | F7: =$B$4 | G7: Tu negocio | H7: Cómo se calcula (referente / tuyo)
A8: Clientes por día | B8: 87 | C8: 18 | E8: Unidades por día | F8: =B8*B9 | G8: =C8*C9 | H8: ="clientes por día ("&B8&" / "&C8&") × unidades por cada cliente ("&B9&" / "&C9&")"
A9: Unidades por cada cliente | B9: 3.5 | C9: 5.6 | E9: Ingreso por día | F9: =F8*B10 | G9: =G8*C10 | H9: ="unidades por día ("&ROUND(F8,1)&" / "&ROUND(G8,1)&") × precio ("&TEXT(B10,"$#,##0")&" / "&TEXT(C10,"$#,##0")&")"
A10: Precio de la unidad | B10: 22 | C10: 55 | E10: Ingreso del mes | F10: =F9*B11 | G10: =G9*C11 | H10: ="ingreso por día ("&TEXT(F9,"$#,##0")&" / "&TEXT(G9,"$#,##0")&") × días abiertos ("&B11&" / "&C11&")"
A11: Días abiertos al mes | B11: 26 | C11: 26 | E11: LOS TRES CAMINOS · CADA UNO MUEVE UNA SOLA COSA
A12: LOS TRES MOVIMIENTOS · los mismos para los dos negocios | E12: Cuánto suma cada camino, moviendo lo de la izquierda.
A13: Clientes nuevos esperados al mes | B13: 2 | E13: ="Si traes "&$B$13&IF($B$13=1," cliente nuevo"," clientes nuevos")&" al mes" | F13: =B9*B10*B11*($B$13/B11) | G13: =C9*C10*C11*($B$13/C11) | H13: ="unidades por cada cliente ("&B9&" / "&C9&") × "&"precio ("&TEXT(B10,"$#,##0")&" / "&TEXT(C10,"$#,##0")&")"&" × "&"días abiertos ("&B11&" / "&C11&")"&" × clientes nuevos al mes, repartidos por día ("&ROUND($B$13/B11,2)&" / "&ROUND($B$13/C11,2)&")"
A14: Unidades adicionales por cliente | B14: 0.31 | E14: ="Si cada cliente lleva "&$B$14&" unidades más" | F14: =B8*B10*B11*$B$14 | G14: =C8*C10*C11*$B$14 | H14: ="clientes por día ("&B8&" / "&C8&") × "&"precio ("&TEXT(B10,"$#,##0")&" / "&TEXT(C10,"$#,##0")&")"&" × "&"días abiertos ("&B11&" / "&C11&")"&" × unidades adicionales ("&$B$14&")"
A15: Días adicionales al mes | B15: 1 | E15: ="Si abres "&$B$15&IF($B$15=1," día"," días")&" más al mes" | F15: =B8*B9*B10*$B$15 | G15: =C8*C9*C10*$B$15 | H15: ="clientes por día ("&B8&" / "&C8&") × unidades por cada cliente ("&B9&" / "&C9&") × "&"precio ("&TEXT(B10,"$#,##0")&" / "&TEXT(C10,"$#,##0")&")"&" × días adicionales ("&$B$15&")"
A16: Los dos negocios no tienen por qué dar la misma respuesta, y ese es el punto: lo que decide es la proporción entre cuánta gente entra y cuánto se lleva cada quien. Compara los tres puntos de quiebre de cada columna y pregúntate cuál de esos tres movimientos está más a tu alcance el mes que entra. Eso no lo contesta ninguna celda. | E16: LA MÉTRICA QUE IMPORTA | F16: =IF(F14>F13,"subirle a cada cliente","traer más clientes") | G16: =IF(G14>G13,"subirle a cada cliente","traer más clientes") | H16: Compara solo dos de los tres renglones de arriba: «Si traes clientes» contra «Si cada cliente lleva más», en pesos. Contar unidades da la misma respuesta. No entra el Camino C, que tiene tope, ni lo que cuesta cada movimiento: eso lo decides tú.
E17: Clientes adicionales con los que ganaría el A | F17: =IF($B$13>=ROUNDUP(MAX(F14,F15)/(B9*B10),0),"Ya ganas · bastaba con "&ROUNDUP(MAX(F14,F15)/(B9*B10),0)&" al mes",ROUNDUP(MAX(F14,F15)/(B9*B10),0)&" al mes") | G17: =IF($B$13>=ROUNDUP(MAX(G14,G15)/(C9*C10),0),"Ya ganas · bastaba con "&ROUNDUP(MAX(G14,G15)/(C9*C10),0)&" al mes",ROUNDUP(MAX(G14,G15)/(C9*C10),0)&" al mes") | H17: ="Cuántos clientes nuevos al mes harían falta para que el Camino A pasara al primer lugar, dejando los otros dos movimientos como están ahora ("&B14&" y "&B15&"). Si mueves cualquiera de esos dos, este número cambia."
A18: VERDE | B18: Escribes tú. | E18: Unidades adicionales con las que ganaría el B | F18: =IF(B14>=ROUNDUP(MAX(F13,F15)/(B8*B10*B11),2),"Ya ganas · bastaba con "&ROUNDUP(MAX(F13,F15)/(B8*B10*B11),2),ROUNDUP(MAX(F13,F15)/(B8*B10*B11),2)) | G18: =IF(B14>=ROUNDUP(MAX(G13,G15)/(C8*C10*C11),2),"Ya ganas · bastaba con "&ROUNDUP(MAX(G13,G15)/(C8*C10*C11),2),ROUNDUP(MAX(G13,G15)/(C8*C10*C11),2)) | H18: ="Lo mismo para el Camino B, con los otros dos movimientos en "&B13&" al mes y "&B15&"."
A19: GRIS | B19: Calculada. No escribas encima. | E19: Días adicionales con los que ganaría el C | F19: =IF(B15>=ROUNDUP(MAX(F13,F14)/(B8*B9*B10),0),"Ya ganas · bastaba con "&ROUNDUP(MAX(F13,F14)/(B8*B9*B10),0),ROUNDUP(MAX(F13,F14)/(B8*B9*B10),0)) | G19: =IF(B15>=ROUNDUP(MAX(G13,G14)/(C8*C9*C10),0),"Ya ganas · bastaba con "&ROUNDUP(MAX(G13,G14)/(C8*C9*C10),0),ROUNDUP(MAX(G13,G14)/(C8*C9*C10),0)) | H19: ="Lo mismo para el Camino C, con los otros dos movimientos en "&B13&" al mes y "&B14&"."

Sheet S01-Lab
A1: FUNDAMENTOS CUANTITATIVOS PARA NEGOCIOS CREATIVOS · SEMANA 1
A2: Auditoría de un referente
A4: CÓMO LEER LOS COLORES
B5: VERDE · celda que tú editas. Cámbiala y todo lo demás se recalcula solo.
B6: AZUL · dato reportado por la fuente. No lo cambies: es el terreno contra el que te comparas.
B7: GRIS · celda calculada por una fórmula. No escribas aquí, se sobrescribe la fórmula.
A9: 1 · PISO, TU SUPUESTO Y TECHO
A10: El piso es el extremo bajo de ventas que reportan las fuentes ($100,000 al mes) y el techo el extremo alto ($300,000). Ninguno es una predicción: juntos marcan el terreno donde es razonable que caiga tu número. La ganancia se queda fija en 10% en las tres filas.
A11: Escenario | B11: Ventas mensuales | C11: Ganancia (% de las ventas) | D11: Ganancia por cada $100k | E11: Ingreso diario | F11: Ganancia diaria | G11: Diferencia vs tu supuesto | H11: Cómo se lee esa diferencia
A12: Piso | B12: 100000 | C12: 0.1 | D12: =B12*C12 | E12: =B12/30 | F12: =E12*C12 | G12: =F12-$F$13 | H12: =IF(G12<0,"Este escenario deja MENOS al día que tu supuesto. Estar por arriba de él es buena señal.",IF(G12>0,"Este escenario deja MÁS al día que tu supuesto: tu supuesto se queda corto frente a él.","Igual que tu supuesto."))
A13: Tu supuesto | B13: 200000 | C13: 0.1 | D13: =B13*C13 | E13: =B13/30 | F13: =E13*C13 | G13: — | H13: Es la fila contra la que se comparan las otras dos.
A14: Techo | B14: 300000 | C14: 0.1 | D14: =B14*C14 | E14: =B14/30 | F14: =E14*C14 | G14: =F14-$F$13 | H14: =IF(G14<0,"Este escenario deja MENOS al día que tu supuesto. Estar por arriba de él es buena señal.",IF(G14>0,"Este escenario deja MÁS al día que tu supuesto: tu supuesto se queda corto frente a él.","Igual que tu supuesto."))
A15: El 10% es LINEAL: es el mismo porcentaje sin importar cuánto vendas, por eso está igual en las tres filas. Si vendes el doble ganas el doble, ni más ni menos. Fórmulas: ingreso diario = ventas del mes ÷ 30 · ganancia diaria = ingreso diario × 10%
A16: Sobre el signo de la columna F: la resta siempre es «esta fila menos tu supuesto». En el Piso sale NEGATIVO y eso es correcto, no es una pérdida: quiere decir que el piso deja menos al día que tu supuesto, o sea que estás por arriba del piso. En el Techo sale positivo porque el techo deja más que tú. Fíjate que las dos diferencias miden lo mismo, $333.33, porque tu supuesto quedó justo a la mitad.
A18: 2 · COMPARACIÓN DE PALANCAS
A19: Dos caminos para subir tu ganancia diaria, los dos partiendo de tu supuesto. El Camino A sube las ventas y deja la ganancia en 10%. El Camino B hace lo contrario: mismas ventas, mejor ganancia.
A20: Escenario | B20: Ventas mensuales | C20: Ganancia (% de las ventas) | D20: Ganancia por cada $100k | E20: Ingreso diario | F20: Ganancia diaria | G20: Diferencia vs tu supuesto | H20: Cómo se lee esa diferencia
A21: Punto de partida (tu supuesto) | B21: =B13 | C21: =C13 | D21: =B21*C21 | E21: =B21/30 | F21: =E21*C21 | G21: — | H21: Es la fila contra la que se comparan los dos caminos.
A22: Camino A · vender más | B22: 250000 | C22: =C13 | D22: =B22*C22 | E22: =B22/30 | F22: =E22*C22 | G22: =F22-$F$21 | H22: Ventas a medio camino entre tu supuesto y el techo reportado. La ganancia no se mueve.
A23: Camino B · ganar mejor | B23: =B13 | C23: 0.15 | D23: =B23*C23 | E23: =B23/30 | F23: =E23*C23 | G23: =F23-$F$21 | H23: La ganancia sube de 10% a 15%. Las ventas no se mueven.
A24: Con estos números gana el Camino B. La pregunta que sigue no la resuelve la hoja: ¿qué te cuesta menos en tu negocio, vender una cuarta parte más, o ganar 5 puntos más de cada venta que ya haces?

Sheet S02-Lab
A1: S02-Lab · DE LOS NÚMEROS A LA ESTRATEGIA
A2: El ingreso de un mes no es un número suelto: es una cadena de proporciones. Cada eslabón se puede mover por separado, y de eso se trata la sesión.
A4: 1 · LOS SUPUESTOS DE TU NEGOCIO
A5: Los cuatro supuestos de tu negocio, tomados del Panel. En azul porque no se mueven aquí: son el terreno contra el que te comparas en este ejercicio.
A6: Supuesto | B6: Valor | C6: Unidad | D6: Qué tipo de proporción es
A7: Clientes por día | B7: =Panel!C8 | C7: clientes por día | D7: Tasa: el segundo término mide tiempo.
A8: Unidades por cada cliente | B8: =Panel!C9 | C8: unidades por cliente | D8: Razón: cuánto se lleva en promedio quien ya entró.
A9: Precio de la unidad | B9: =Panel!C10 | C9: pesos por unidad | D9: Razón: pesos por cada unidad.
A10: Días abiertos al mes | B10: =Panel!C11 | C10: días por mes | D10: Tasa: cuántos días del mes vende de verdad.
A11: ="Estado de los cuatro supuestos: "&IF(AND(B7=18,B8=5.6,B9=55,B10=26),"estás en los números de tu negocio, tal como están en el Panel.","estás explorando. Los de tu negocio en el Panel son 18 clientes por día, 5.6 unidades por cliente, $55 la unidad y 26 días abiertos.")
A12: 2 · LO QUE MOVEMOS
A13: Los tres movimientos que podemos dar, en celdas verdes y juntas a propósito. Cada camino del bloque 4 mueve uno de ellos y deja quietos los otros dos. Cambia cualquiera y toda la hoja se recalcula.
A14: Movimiento | B14: Valor | C14: Unidad | D14: Cómo se lee en el negocio
A15: Clientes nuevos esperados al mes | B15: 26 | C15: clientes por mes | D15: ="Piénsalo por mes, no por día: no hay medio cliente, así que va en enteros. Ahora está en "&B15&"."
A16: → repartidos entre los días abiertos | B16: =B15/B10 | C16: clientes por día (promedio) | D16: ="Si repartes "&B15&" clientes nuevos entre los "&B10&" días que abres, son "&ROUND(B16,2)&" por día en promedio. No hace falta que lleguen parejo: la hoja solo necesita el total del mes."
A17: Unidades adicionales por cliente | B17: 0.2 | C17: unidades por cliente | D17: ="Nadie pide "&B17&" unidades. Es un promedio: es como si "&ROUND(B17*10,1)&" de cada 10 clientes se llevaran una unidad más. Puede llevar decimales."
A18: Días adicionales al mes | B18: 1 | C18: días por mes | D18: ="Abrir "&B18&IF(B18=1," día que antes se cerraba"," días que antes se cerraban")&", por ejemplo un domingo. Va en enteros y el mes se acaba: no puede pasar de 31 menos los que ya abres."
A20: 3 · EL MES ACTUAL
A21: La cadena completa tal como está hoy, sin mover nada. Cada renglón usa el de arriba.
A22: Resultado | B22: Valor | D22: Cómo se calcula
A23: Unidades por día | B23: =B7*B8 | D23: ="clientes por día ("&B7&") × unidades por cada cliente ("&B8&")"
A24: Ingreso por día | B24: =B23*B9 | D24: ="unidades por día ("&ROUND(B23,1)&") × precio de la unidad ("&TEXT(B9,"$#,##0")&")"
A25: Ingreso por mes | B25: =B24*B10 | D25: ="ingreso por día ("&TEXT(B24,"$#,##0")&") × días abiertos al mes ("&B10&")"
A27: 4 · CUÁNTO SUMA CADA CAMINO
A28: Las tres fórmulas tienen la misma forma: todos los números del negocio, menos el que estás moviendo, multiplicados por el movimiento que le das. El número que falta no se olvidó: lo reemplaza el movimiento.
A29: Camino | B29: Cuánto suma al mes | C29: Cómo se calcula | D29: Por qué
A30: Camino A · más clientes | B30: =B8*B9*B10*B16 | C30: ="unidades por cliente ("&B8&") × precio ("&TEXT(B9,"$#,##0")&") × días abiertos ("&B10&") × clientes adicionales por día ("&ROUND(B16,2)&")" | D30: Trae todos los números del negocio menos «clientes por día», porque ese es justo el que estás moviendo: lo reemplaza el movimiento. El cliente extra se lleva lo que se lleva cualquiera.
A31: Camino B · más unidades por cliente | B31: =B7*B9*B10*B17 | C31: ="clientes por día ("&B7&") × precio ("&TEXT(B9,"$#,##0")&") × días abiertos ("&B10&") × unidades adicionales ("&B17&")" | D31: Trae todos menos «unidades por cada cliente», por la misma razón. Esa fracción extra se cobra en cada uno de los clientes que ya entran.
A32: Camino C · más días abiertos | B32: =B7*B8*B9*B18 | C32: ="clientes por día ("&B7&") × unidades por cliente ("&B8&") × precio ("&TEXT(B9,"$#,##0")&") × días adicionales ("&B18&")"
A33: Los tres números son POR MES, incluido el Camino C. Que el Camino C coincida con el ingreso de un día no es porque cambie de unidad: es porque agregar un día al mes le suma al mes exactamente lo que vende un día. El Camino C sigue sin competir con los otros dos, porque el mes tiene entre 28 y 31 días y ahí se acaba.
A35: 5 · EL MES SI MUEVES UNA SOLA COSA
A36: Lo mismo de arriba, ya sumado al mes. Aquí se ve el tamaño real de cada decisión.
A37: Escenario | B37: Total del mes | C37: Cuánto más que el mes actual | D37: Qué se movió
A38: Hoy, sin mover nada | B38: =B25 | C38: — | D38: no se movió nada: es el mes actual.
A39: Con el Camino A | B39: =B25+B30 | C39: =B39-B38 | D39: ="con "&B15&" clientes nuevos al mes (≈"&ROUND(B16,2)&" por día), el día promedio pasa de "&B7&" a "&ROUND(B7+B16,2)&" clientes."
A40: Con el Camino B | B40: =B25+B31 | C40: =B40-B38 | D40: ="unidades por cada cliente: "&B8&" + "&B17&" = "&ROUND(B8+B17,2)
A41: Con el Camino C | B41: =B25+B32 | C41: =B41-B38 | D41: ="días abiertos al mes: "&B10&" + "&B18&" = "&B10+B18
A42: ="El que más suma es el Camino "&IF(AND(B30>=B31,B30>=B32),"A",IF(B31>=B32,"B","C"))&". No es que esa palanca sea mejor que las otras: es que el movimiento que le pusimos es el más grande de los tres comparado con la base sobre la que cae. Cada camino tiene su punto de quiebre, y aquí están: el Camino A ganaría con "&ROUNDUP(MAX(B31,B32)/(B8*B9*B10),0)&" clientes adicionales al día en promedio (hoy vas en "&ROUND(B16,2)&", equivalente a "&B15&" al mes); al Camino B le bastarían "&ROUNDUP(MAX(B30,B32)/(B7*B9*B10),2)&" unidades por cliente; y el Camino C ganaría con "&ROUNDUP(MAX(B30,B31)/(B7*B8*B9),0)&" días. Cámbialos en el bloque 2 y vuelve a mirar aquí: el que gana cambia. Fíjate en cuál de esos tres movimientos está más a tu alcance en la vida real, porque eso no lo contesta la hoja. Y el Camino C no compite del todo: el mes tiene entre 28 y 31 días"&" y ahí se acaba."

Sheet Vocabulario
A1: VOCABULARIO ACUMULADO
A2: Las definiciones son las mismas del glosario de la app. Se consultan, no se reescriben.
A4: SEMANA 1 · ¿POR QUÉ LOS NÚMEROS?
A5: Término | B5: Definición | C5: Semana | D5: Categoría
A6: Dato | B6: Un valor concreto que se observa o se mide: cuánto cobra un competidor, cuántas personas pasan frente a un local en una hora, cuánto cuesta un insumo. | C6: 1 | D6: general
A7: Métrica | B7: El dato que sí importa seguir de cerca porque de él depende una decisión. No todos los datos son igual de importantes. | C7: 1 | D7: general
A8: Modelo | B8: Una versión simplificada de la realidad de un negocio que se usa para tomar una decisión concreta: cuánto cobrar, cuánta gente necesito, si el negocio se sostiene. | C8: 1 | D8: general
A9: Referente | B9: Un negocio que ya existe y que sirve de comparación. Sus números, aunque no sean exactos para tu caso, dan una primera idea de qué esperar. | C9: 1 | D9: general
A10: Supuesto | B10: Algo que el modelo da por cierto sin haberlo confirmado todavía. Nombrarlo es lo que permite revisar el modelo después, cuando lleguen datos reales. | C10: 1 | D10: general
A11: Piso | B11: El resultado más bajo que es razonable esperar, calculado usando el extremo conservador de lo que reportan negocios parecidos al tuyo. No es la predicción de un desastre ni el peor caso imaginable: es el borde de abajo del terreno donde tiene sentido que caiga tu número. | C11: 1 | D11: general
A12: Techo | B12: El resultado más alto que es razonable esperar, calculado usando el extremo favorable de lo que reportan negocios parecidos al tuyo. Es el borde de arriba del mismo terreno que marca el piso, no una meta ni una promesa. | C12: 1 | D12: general
A14: SEMANA 2 · DE LOS NÚMEROS A LA ESTRATEGIA
A15: Término | B15: Definición | C15: Semana | D15: Categoría
A16: Proporción / razón | B16: La comparación entre dos cantidades que dice qué tanto corresponde de una por cada unidad de la otra: por ejemplo, unidades por cada cliente. | C16: 2 | D16: matematico
A17: Tasa | B17: Una proporción donde el segundo término es tiempo, como clientes por día o ventas por mes. | C17: 2 | D17: matematico
A18: La métrica que importa | B18: La palanca que, con los supuestos actuales del negocio, más mueve el resultado si se mueve ella. No es la única métrica del negocio, es la más sensible en un momento dado. | C18: 2 | D18: negocio
A19: Palanca | B19: Un número del modelo que, al cambiarlo, cambia el resultado; distintas palancas mueven el resultado en distinta medida. | C19: 2 | D19: negocio
A20: Tablero de supuestos | B20: El conjunto de supuestos de un negocio puestos juntos y editables, para poder preguntar qué pasaría si alguno de esos números fuera distinto. | C20: 2 | D20: negocio
A21: Unidad | B21: La palabra que dice qué está contando un número: no es lo mismo 87 que "87 clientes por día". Todo valor del tablero va acompañado de su unidad, porque un número solo no dice nada. | C21: 2 | D21: matematico
A22: Valor | B22: El número concreto de un supuesto o de un movimiento. Va siempre junto a su unidad, en la columna de al lado: un valor solo, sin unidad, no dice qué está midiendo. | C22: 2 | D22: matematico

Sheet Comprobación
A1: COMPROBACIÓN · verificación por segundo método
A2: Cada renglón recalcula un resultado por una ruta distinta a la que usa la celda. No hay valores escritos a mano. Esta pestaña es del docente y no va en el archivo del alumno.
A4: Qué se verifica | B4: Lo que hay | C4: Verificación | D4: Diferencia | E4: Estado | F4: Por qué camino se verifica
A5: S02-Lab · ingreso del mes | B5: ='S02-Lab'!B25 | C5: ='S02-Lab'!B7*'S02-Lab'!B8*'S02-Lab'!B9*'S02-Lab'!B10 | D5: =B5-C5 | E5: =IF(ABS(D5)<0.01,"OK","revisar") | F5: los cuatro supuestos de un jalón, sin pasar por el ingreso diario ni el ingreso por mes
A6: S02-Lab · Camino A (clientes nuevos) | B6: ='S02-Lab'!B30 | C6: ='S02-Lab'!B8*'S02-Lab'!B9*'S02-Lab'!B15 | D6: =B6-C6 | E6: =IF(ABS(D6)<0.01,"OK","revisar") | F6: usa que los días abiertos se cancelan algebraicamente: no pasa por B16
A7: S02-Lab · Camino B (unidades por cliente) | B7: ='S02-Lab'!B31 | C7: ='S02-Lab'!B24*('S02-Lab'!B17/'S02-Lab'!B8)*'S02-Lab'!B10 | D7: =B7-C7 | E7: =IF(ABS(D7)<0.01,"OK","revisar") | F7: recalcula desde el ingreso por día, no desde los cuatro supuestos sueltos
A8: S02-Lab · Camino C (días adicionales) | B8: ='S02-Lab'!B32 | C8: ='S02-Lab'!B23*'S02-Lab'!B9*'S02-Lab'!B18 | D8: =B8-C8 | E8: =IF(ABS(D8)<0.01,"OK","revisar") | F8: recalcula desde unidades por día, no desde los cuatro supuestos sueltos
A9: S02-Lab · el mes con el Camino C | B9: ='S02-Lab'!B41 | C9: ='S02-Lab'!B24*('S02-Lab'!B10+'S02-Lab'!B18) | D9: =B9-C9 | E9: =IF(ABS(D9)<0.01,"OK","revisar") | F9: ingreso por día por los días totales del mes, en vez de sumar el camino aparte
A10: S02-Lab · sus supuestos vienen del Panel | B10: ='S02-Lab'!B7 | C10: =Panel!C8 | D10: =B10-C10 | E10: =IF(ABS(D10)<0.01,"OK","revisar") | F10: confirma que el enlace a Tu Negocio del Panel esté vivo, no copiado a mano
A11: Panel · el mes, referente | B11: =Panel!F10 | C11: =Panel!B8*Panel!B9*Panel!B10*Panel!B11 | D11: =B11-C11 | E11: =IF(ABS(D11)<0.01,"OK","revisar") | F11: los cuatro supuestos del referente de un jalón, sin pasar por ingreso por día
A12: Panel · el mes, tu negocio | B12: =Panel!G10 | C12: =Panel!C8*Panel!C9*Panel!C10*Panel!C11 | D12: =B12-C12 | E12: =IF(ABS(D12)<0.01,"OK","revisar") | F12: los cuatro supuestos de tu negocio de un jalón, sin pasar por ingreso por día
A13: Panel · Camino A, referente | B13: =Panel!F13 | C13: =Panel!B9*Panel!B10*Panel!$B$13 | D13: =B13-C13 | E13: =IF(ABS(D13)<0.01,"OK","revisar") | F13: usa que los días abiertos se cancelan: no pasa por B11 ni por la división
A14: Panel · Camino A, tu negocio | B14: =Panel!G13 | C14: =Panel!C9*Panel!C10*Panel!$B$13 | D14: =B14-C14 | E14: =IF(ABS(D14)<0.01,"OK","revisar") | F14: usa que los días abiertos se cancelan: no pasa por C11 ni por la división
A17: Resultado | B17: =COUNTIF(E5:E14,"OK")&" de "&COUNTA(E5:E14)&" en orden" | D17: =IF(COUNTIF(E5:E14,"revisar")>0,"Hay algo que revisar.","Ninguna diferencia.")
